atoti_jupyterlab/__init__.py
atoti_jupyterlab/py.typed
atoti_jupyterlab-0.9.12.data/data/share/jupyter/labextensions/@atoti/jupyterlab-extension/package.json
atoti_jupyterlab-0.9.12.data/data/share/jupyter/labextensions/@atoti/jupyterlab-extension/static/00b26ac825e209505639.woff2
atoti_jupyterlab-0.9.12.data/data/share/jupyter/labextensions/@atoti/jupyterlab-extension/static/036d4e95149b69ff9bcc.woff2
atoti_jupyterlab-0.9.12.data/data/share/jupyter/labextensions/@atoti/jupyterlab-extension/static/07d8e303ce4fc12b4bb5.ttf
atoti_jupyterlab-0.9.12.data/data/share/jupyter/labextensions/@atoti/jupyterlab-extension/static/08ce98e51b04d58945a3.ttf
atoti_jupyterlab-0.9.12.data/data/share/jupyter/labextensions/@atoti/jupyterlab-extension/static/0cdd387c9590a1a9f979.woff2
atoti_jupyterlab-0.9.12.data/data/share/jupyter/labextensions/@atoti/jupyterlab-extension/static/0d85ae7cc30f23790a7f.ttf
atoti_jupyterlab-0.9.12.data/data/share/jupyter/labextensions/@atoti/jupyterlab-extension/static/0f60d1b897938ec918c8.woff2
atoti_jupyterlab-0.9.12.data/data/share/jupyter/labextensions/@atoti/jupyterlab-extension/static/1028.93c2e750e606ffefdb99.js
atoti_jupyterlab-0.9.12.data/data/share/jupyter/labextensions/@atoti/jupyterlab-extension/static/11e4dc8a6471ff6d6ee5.woff
atoti_jupyterlab-0.9.12.data/data/share/jupyter/labextensions/@atoti/jupyterlab-extension/static/1362.0910ed30b064cd902169.js
atoti_jupyterlab-0.9.12.data/data/share/jupyter/labextensions/@atoti/jupyterlab-extension/static/1362.0910ed30b064cd902169.js.LICENSE.txt
atoti_jupyterlab-0.9.12.data/data/share/jupyter/labextensions/@atoti/jupyterlab-extension/static/1382.a2b01be83bb1d831bddb.js
atoti_jupyterlab-0.9.12.data/data/share/jupyter/labextensions/@atoti/jupyterlab-extension/static/138ac28d1663b3037e9c.ttf
atoti_jupyterlab-0.9.12.data/data/share/jupyter/labextensions/@atoti/jupyterlab-extension/static/1443.7059a192ef3ff80772af.js
atoti_jupyterlab-0.9.12.dist-info/WHEEL
atoti_jupyterlab-0.9.12.dist-info/METADATA
atoti_jupyterlab-0.9.12.dist-info/RECORD
