Metadata-Version: 2.3
Name: atoti-jupyterlab
Version: 0.9.12
Summary: Extension to create interactive Atoti widgets in JupyterLab
Keywords: atoti,chart,dataviz,interactive,jupyter,jupyterlab,kpi,pivot-table,visualization
Author: ActiveViam
Author-email: ActiveViam <atoti-dev@activeviam.com>
Classifier: Development Status :: 4 - Beta
Classifier: Framework :: Jupyter
Classifier: License :: Free for non-commercial use
Classifier: Operating System :: OS Independent
Classifier: Programming Language :: Java
Classifier: Programming Language :: JavaScript
Classifier: Programming Language :: Python :: 3
Classifier: Topic :: Scientific/Engineering :: Visualization
Classifier: Typing :: Typed
Requires-Dist: atoti-core==0.9.12
Requires-Dist: jupyterlab>=4.3.5
Requires-Python: >=3.10
Project-URL: Documentation, https://docs.activeviam.com/products/atoti/python-sdk/0.9.12/api/atoti_jupyterlab.html
Project-URL: Homepage, https://www.atoti.io
Project-URL: Issues, https://github.com/atoti/atoti/issues
